kadap/__init__.py
kadap/data.py
kadap/benchmarking/__init__.py
kadap/benchmarking/benchmarking_result.py
kadap/config/__init__.py
kadap/config/config.py
kadap/linked/__init__.py
kadap/linked/linked_data.py
kadap/retained/__init__.py
kadap/retained/retained_data.py
kadap/vin/__init__.py
kadap/vin/vin_decoder.py
kadap-0.1.3.dist-info/LICENSE
kadap-0.1.3.dist-info/METADATA
kadap-0.1.3.dist-info/WHEEL
kadap-0.1.3.dist-info/top_level.txt
kadap-0.1.3.dist-info/RECORD
