Metadata-Version: 2.1
Name: kadap
Version: 0.1.3
Summary: This is kadap test package
Home-page: UNKNOWN
Author: 이종근(jklee2)
Author-email: jklee2@katech.re.kr
License: MIT
Platform: UNKNOWN
Classifier: Programming Language :: Python :: 3
Classifier: License :: OSI Approved :: MIT License
Classifier: Operating System :: OS Independent
Requires-Dist: numpy
Requires-Dist: opencv-python
Requires-Dist: requests
